pymegatools/__init__.py
pymegatools/pymegatools.py
pymegatools-1.0.2.dist-info/METADATA
pymegatools-1.0.2.dist-info/WHEEL
pymegatools-1.0.2.dist-info/top_level.txt
pymegatools-1.0.2.dist-info/RECORD
