Metadata-Version: 2.1
Name: pymegatools
Version: 1.0.2
Summary: Simple Python wrapper for the megatools cmdline utility.
Home-page: https://github.com/justaprudev/pymegatools
Author: justaprudev
License: UNKNOWN
Platform: UNKNOWN
Classifier: Programming Language :: Python
Classifier: License :: OSI Approved
Classifier: Operating System :: OS Independent
Requires-Python: >=3.9
